pyrra/__init__.py
pyrra/beta_scores.py
pyrra/rank_matrix.py
pyrra/rho_scores.py
pyrra-0.1.1.dist-info/licenses/LICENSE
pyrra-0.1.1.dist-info/METADATA
pyrra-0.1.1.dist-info/WHEEL
pyrra-0.1.1.dist-info/top_level.txt
pyrra-0.1.1.dist-info/RECORD
